simlx/__init__.py
simlx/foo.py
simlx/data/__init__.py
simlx/data/tools.py
simlx/data/loaders/__init__.py
simlx/data/loaders/base.py
simlx/models/__init__.py
simlx/models/decoder_head.py
simlx/models/mamba_vit_encoder.py
simlx/models/matryoshka_unet.py
simlx/models/normalization.py
simlx/models/projection_utils.py
simlx/models/random_projection.py
simlx/models/registry.py
simlx/models/vit_encoder.py
simlx/models/base/__init__.py
simlx/models/base/base_model.py
simlx/tracking/__init__.py
simlx/tracking/base.py
simlx/tracking/clearml_adapter.py
simlx/tracking/mlflow_adapter.py
simlx/training/__init__.py
simlx/training/communityofpractice/__init__.py
simlx/training/communityofpractice/trainer.py
simlx/utils/__init__.py
simlx/utils/logging.py
simlx-0.1.0.dist-info/METADATA
simlx-0.1.0.dist-info/WHEEL
simlx-0.1.0.dist-info/licenses/LICENSE
simlx-0.1.0.dist-info/RECORD
