Metadata-Version: 2.4
Name: simlx
Version: 0.1.0
Summary: self supervised representation learning
Project-URL: Homepage, https://phzwart.github.io/simlx/
Project-URL: Repository, https://github.com/phzwart/simlx
Project-URL: Documentation, https://phzwart.github.io/simlx/
Author-email: Petrus Zwart <phzwart@lbl.gov>
License-File: LICENSE
Keywords: python
Classifier: Intended Audience :: Developers
Classifier: Programming Language :: Python
Classifier: Programming Language :: Python :: 3
Classifier: Programming Language :: Python :: 3.9
Classifier: Programming Language :: Python :: 3.10
Classifier: Programming Language :: Python :: 3.11
Classifier: Programming Language :: Python :: 3.12
Classifier: Programming Language :: Python :: 3.13
Classifier: Topic :: Software Development :: Libraries :: Python Modules
Requires-Python: <4.0,>=3.9
Requires-Dist: torch>=2.0.0
Provides-Extra: dev
Requires-Dist: bandit>=1.7.9; extra == 'dev'
Requires-Dist: deptry>=0.23.0; extra == 'dev'
Requires-Dist: mkdocs-material>=8.5.10; extra == 'dev'
Requires-Dist: mkdocs>=1.4.2; extra == 'dev'
Requires-Dist: mkdocstrings[python]>=0.26.1; extra == 'dev'
Requires-Dist: mypy>=1.11.0; extra == 'dev'
Requires-Dist: pre-commit>=2.20.0; extra == 'dev'
Requires-Dist: pytest-cov>=4.0.0; extra == 'dev'
Requires-Dist: pytest>=7.2.0; extra == 'dev'
Requires-Dist: ruff>=0.11.5; extra == 'dev'
Requires-Dist: tox-uv>=1.11.3; extra == 'dev'
Requires-Dist: ty>=0.0.1a16; extra == 'dev'
